yt2t/__init__.py
yt2t/main.py
yt2t-0.1.1.dist-info/LICENSE
yt2t-0.1.1.dist-info/METADATA
yt2t-0.1.1.dist-info/WHEEL
yt2t-0.1.1.dist-info/entry_points.txt
yt2t-0.1.1.dist-info/top_level.txt
yt2t-0.1.1.dist-info/RECORD
