Metadata-Version: 2.1
Name: yt2t
Version: 0.1.1
Summary: Extract audio from YouTube videos or local audio files and convert it into text.
License: Apache License 2.0
Requires-Python: >=3.10
License-File: LICENSE
Requires-Dist: pytube ==15.0.0
Requires-Dist: moviepy ==1.0.3
Requires-Dist: openai-whisper ==20231117
Requires-Dist: pydub ==0.25.1
Requires-Dist: youtube-transcript-api ==0.6.2
